{
  "agent_name": "ReportGenerator",
  "execution_status": "Success",
  "execution_date": "2025-11-19",
  "quality_gate_status": "PASSED",
  "report_format": "Comprehensive Markdown Document",
  "report_location": "sessions/session_001/FINAL_INVESTMENT_REPORT.md",
  "report_sections": {
    "executive_summary": "Top 3 recommendations with immediate action plan",
    "market_sector_analysis": "MoneyFlowAnalyzer results - 3 bullish sectors identified",
    "company_screening": "CompanyFinder results - 14 candidates from 45 screened",
    "fundamental_analysis": "FundamentalAnalyzer scores and rankings",
    "technical_analysis": "TechnicalAnalyzer entry recommendations and setups",
    "final_rankings": "RankingEngine combined scores (fundamental 60% + technical 40%)",
    "trading_plans": "EntryExitPlanner detailed execution strategies",
    "risk_management": "Comprehensive risk framework and portfolio rules",
    "disclaimers": "Investment risks and important warnings",
    "monitoring_guidance": "Ongoing tracking and rebalancing instructions",
    "appendices": "Data sources, methodology, and references"
  },
  "top_3_recommendations": [
    {
      "rank": 1,
      "symbol": "INARI.KL",
      "company": "Inari Amertron Berhad",
      "final_score": 8.56,
      "allocation": "12% (RM6,000)",
      "action": "BUY NOW",
      "entry_price": "3.02-3.18",
      "thesis": "Premium semiconductor with fortress balance sheet and AI infrastructure boom tailwind"
    },
    {
      "rank": 2,
      "symbol": "PGAS.KL",
      "company": "Petronas Gas Berhad",
      "final_score": 8.38,
      "allocation": "10% (RM5,000)",
      "action": "BUY NOW",
      "entry_price": "15.85-16.35",
      "thesis": "Gas monopoly with highest utility profitability and strong technical breakout setup"
    },
    {
      "rank": 3,
      "symbol": "PENTA.KL",
      "company": "Pentamaster Corporation Berhad",
      "final_score": 8.44,
      "allocation": "10% (RM5,000)",
      "action": "WAIT for pullback",
      "entry_price": "4.88-5.10 (current 5.25 too high)",
      "thesis": "Outstanding ROE 18.2% with near net-cash, but RSI overbought - patience required"
    }
  ],
  "portfolio_summary": {
    "total_positions": 12,
    "immediate_buy_count": 7,
    "wait_for_pullback_count": 3,
    "avoided_count": 2,
    "total_capital": 50000,
    "immediate_deployment": 34000,
    "reserved_for_pullbacks": 13000,
    "cash_flexibility": 3000,
    "sector_allocation": {
      "Technology": "32%",
      "Finance": "38%",
      "Utilities": "30%"
    },
    "expected_portfolio_metrics": {
      "dividend_yield": "4.65%",
      "weighted_roe": "14.2%",
      "revenue_growth_cagr": "10.8%",
      "expected_return_12m": "15-21%"
    }
  },
  "immediate_action_plan": {
    "week_1_deployment": 34000,
    "day_1_priorities": [
      "INARI.KL - Buy 60% at 3.08-3.15 (RM3,600)",
      "PBBANK.KL - Buy 70% at 4.65-4.72 (RM4,200)",
      "PGAS.KL - Buy 75% at 16.10-16.30 (RM3,750)",
      "MAXIS.KL - Buy 70% at 3.65-3.72 (RM3,500)"
    ],
    "days_2_3_execution": [
      "MAYBANK.KL - Buy 75% at 10.35-10.50 (RM3,375)",
      "CIMB.KL - Buy 70% at 7.85-7.98 (RM2,450)",
      "TENAGA.KL - Buy 75% at 11.75-11.92 (RM3,000)"
    ],
    "weeks_2_3_patience": [
      "PENTA.KL - Wait for dip to 4.88-5.10 (DO NOT CHASE at 5.25)",
      "UNISEM.KL - Scale in on dips to 4.45-4.72",
      "GREATEC.KL - Wait for pullback to 4.15-4.40"
    ]
  },
  "critical_warnings": [
    "DO NOT CHASE PENTA.KL at current price 5.25 - RSI 68.2 overbought, wait for 7-10% pullback",
    "AVOID VSOLAR.KL completely - Parabolic rally RSI 71.5, high risk of 20-30% correction",
    "ALWAYS honor stop losses - No exceptions, no averaging down below stops",
    "Keep minimum 5% cash reserve (RM2,500) - Do not deploy all capital immediately",
    "Monitor quarterly earnings - Exit if fundamental scores drop >1.0 point"
  ],
  "report_statistics": {
    "total_pages": "~35-40 pages",
    "total_words": "~12,000 words",
    "sections": 10,
    "appendices": 3,
    "data_tables": 15,
    "position_trading_plans": 10,
    "risk_scenarios": 3
  },
  "quality_validation": {
    "all_7_stages_consolidated": true,
    "executive_summary_clear": true,
    "actionable_recommendations": true,
    "risk_disclaimers_comprehensive": true,
    "monitoring_guidance_provided": true,
    "data_sources_documented": true,
    "user_profile_aligned": true,
    "quality_gate_status": "PASSED ✓"
  },
  "all_artifacts_created": [
    "sessions/session_001/reports/sector_analysis.json",
    "sessions/session_001/reports/company_candidates.json",
    "sessions/session_001/reports/fundamental_scores.json",
    "sessions/session_001/reports/technical_analysis.json",
    "sessions/session_001/reports/final_rankings.json",
    "sessions/session_001/reports/entry_exit_plans.json",
    "sessions/session_001/FINAL_INVESTMENT_REPORT.md",
    "sessions/session_001/handoffs/handoff-MoneyFlowAnalyzer.json",
    "sessions/session_001/handoffs/handoff-CompanyFinder.json",
    "sessions/session_001/handoffs/handoff-FundamentalAnalyzer.json",
    "sessions/session_001/handoffs/handoff-TechnicalAnalyzer.json",
    "sessions/session_001/handoffs/handoff-RankingEngine.json",
    "sessions/session_001/handoffs/handoff-EntryExitPlanner.json"
  ],
  "expert_system_completion": "ALL 7 AGENTS EXECUTED SUCCESSFULLY ✓",
  "agent_completion_timestamp": "2025-11-19T00:00:00Z"
}
